ombralis/__init__.py
ombralis/core/__init__.py
ombralis/core/datatypes.py
ombralis/core/graph_program.py
ombralis/core/pipeline.py
ombralis/embeddings/__init__.py
ombralis/embeddings/embeddings.py
ombralis/embeddings/fake.py
ombralis/embeddings/ollama.py
ombralis/embeddings/sentence_transformer.py
ombralis/loaders/dataset_loader.py
ombralis/loaders/graph_program_loader.py
ombralis/memory/__init__.py
ombralis/memory/document_memory.py
ombralis/memory/fact_memory.py
ombralis/memory/integration/__init__.py
ombralis/memory/integration/falkordb/__init__.py
ombralis/memory/integration/falkordb/falkordb_document_memory.py
ombralis/memory/integration/falkordb/falkordb_fact_memory.py
ombralis/memory/integration/falkordb/falkordb_memory.py
ombralis/memory/integration/falkordb/falkordb_program_memory.py
ombralis/memory/integration/falkordb/falkordb_trace_memory.py
ombralis/memory/integration/local/__init__.py
ombralis/memory/integration/local/local_document_memory.py
ombralis/memory/integration/local/local_fact_memory.py
ombralis/memory/integration/local/local_memory.py
ombralis/memory/integration/local/local_program_memory.py
ombralis/memory/integration/local/local_trace_memory.py
ombralis/memory/program_memory.py
ombralis/memory/trace_memory.py
ombralis/metrics/agents/correct_answer.py
ombralis/metrics/agents/factual_answer.py
ombralis/metrics/agents/helpful_interaction.py
ombralis/metrics/documents/documents_similarity.py
ombralis/metrics/facts/facts_similarity.py
ombralis/metrics/metric.py
ombralis/modules/__init__.py
ombralis/modules/agents/__init__.py
ombralis/modules/agents/graph_interpreter.py
ombralis/modules/agents/tools/__init__.py
ombralis/modules/agents/tools/add_document.py
ombralis/modules/agents/tools/add_fact.py
ombralis/modules/agents/tools/add_graph_program.py
ombralis/modules/agents/tools/ask_user.py
ombralis/modules/agents/tools/call_graph_program.py
ombralis/modules/agents/tools/chain_of_thought.py
ombralis/modules/agents/tools/document_search.py
ombralis-1.2.1.dist-info/LICENSE
ombralis-1.2.1.dist-info/METADATA
ombralis-1.2.1.dist-info/WHEEL
ombralis-1.2.1.dist-info/RECORD
