Metadata-Version: 2.1
Name: ombralis
Version: 1.2.1
Summary: The Adaptive Cypher-Driven Neuro-Symbolic AGI Platform
Author: Vesperium AI
Requires-Python: >=3.10,<=3.12.3
Classifier: Development Status :: 3 - Alpha
Classifier: Intended Audience :: Science/Research
Classifier: License :: OSI Approved :: GNU General Public License v3 (GPLv3)
Classifier: Operating System :: POSIX :: Linux
Classifier: Programming Language :: Python :: 3
Classifier: Programming Language :: Python :: 3.10
Classifier: Programming Language :: Python :: 3.11
Classifier: Programming Language :: Python :: 3.12
Classifier: Programming Language :: Python :: 3.9
Requires-Dist: accelerate (>=0.32.1,<0.33.0)
Requires-Dist: colorama (>=0.4.6)
Requires-Dist: datasets (>=2.20.0,<3.0.0)
Requires-Dist: debugpy (==1.8.2)
Requires-Dist: dspy-ai (==2.4.10)
Requires-Dist: faiss-cpu (>=1.8.0.post1)
Requires-Dist: falkordb (>=1.0.7)
Requires-Dist: jinja2 (>=3.1.4,<4.0.0)
Requires-Dist: networkx (>=3.3,<4.0)
Requires-Dist: ollama (>=0.3.3)
Requires-Dist: pyjson5 (>=1.6.6,<2.0.0)
Requires-Dist: pypdf (>=4.3.1,<5.0.0)
Requires-Dist: pytest (>=8.2.2)
Requires-Dist: python-dotenv (>=1.0.1,<2.0.0)
Requires-Dist: pyvis (>=0.3.2,<0.4.0)
Requires-Dist: sentence-transformers (>=2.6.0)
Requires-Dist: tabulate (>=0.9.0,<0.10.0)
Requires-Dist: thefuzz (>=0.22.1,<0.23.0)
Requires-Dist: torch (>=2.3.1,<3.0.0)
Requires-Dist: tqdm (>=4.66.5,<5.0.0)
Requires-Dist: transformers (>=4.42.4,<5.0.0)
